README.md
setup.py
anoncreds/__init__.py
anoncreds/__metadata__.py
anoncreds/manifest.txt
anoncreds/protocol/__init__.py
anoncreds/protocol/exceptions.py
anoncreds/protocol/globals.py
anoncreds/protocol/issuer.py
anoncreds/protocol/prover.py
anoncreds/protocol/public_params_builder.py
anoncreds/protocol/types.py
anoncreds/protocol/utils.py
anoncreds/protocol/verifier.py
anoncreds/protocol/primary/__init__.py
anoncreds/protocol/primary/primary_claim_issuer.py
anoncreds/protocol/primary/primary_proof_builder.py
anoncreds/protocol/primary/primary_proof_common.py
anoncreds/protocol/primary/primary_proof_verifier.py
anoncreds/protocol/repo/__init__.py
anoncreds/protocol/repo/attributes_repo.py
anoncreds/protocol/repo/public_repo.py
anoncreds/protocol/revocation/__init__.py
anoncreds/protocol/revocation/accumulators/__init__.py
anoncreds/protocol/revocation/accumulators/non_revocation_claim_issuer.py
anoncreds/protocol/revocation/accumulators/non_revocation_common.py
anoncreds/protocol/revocation/accumulators/non_revocation_proof_builder.py
anoncreds/protocol/revocation/accumulators/non_revocation_proof_verifier.py
anoncreds/protocol/wallet/__init__.py
anoncreds/protocol/wallet/issuer_wallet.py
anoncreds/protocol/wallet/prover_wallet.py
anoncreds/protocol/wallet/wallet.py
anoncreds/test/__init__.py
anoncreds/test/__main__.py
anoncreds/test/conftest.py
anoncreds/test/run_tests_multiple_times.py
anoncreds/test/test_anoncred_usage.py
anoncreds/test/test_base_wallet.py
anoncreds/test/test_find_claims_for_input.py
anoncreds/test/test_interoperability_with_libindy_pyindy_is_issuer.py
anoncreds/test/test_interoperability_with_libindy_pyindy_is_prover.py
anoncreds/test/test_interoperability_with_libindy_pyindy_is_verifier.py
anoncreds/test/test_multiple_prover_multiple_issuers.py
anoncreds/test/test_non_revocation.py
anoncreds/test/test_quad_equation_lagranges.py
anoncreds/test/test_single_prover_multiple_issuers.py
anoncreds/test/test_single_prover_single_issuer.py
indy_anoncreds.egg-info/PKG-INFO
indy_anoncreds.egg-info/SOURCES.txt
indy_anoncreds.egg-info/dependency_links.txt
indy_anoncreds.egg-info/requires.txt
indy_anoncreds.egg-info/top_level.txt