Metadata-Version: 1.0
Name: indy-anoncreds
Version: 1.0.11
Summary: Anonymous credentials
Home-page: https://github.com/hyperledger/indy-anoncreds
Author: Hyperledger
Author-email: hyperledger-indy@lists.hyperledger.org
License: Apache 2.0
Keywords: Anonymous credentials
Platform: UNKNOWN
